MANIFEST.in
setup.py
bin/moddump
moddump/__init__.py
moddump/abilities.py
moddump/dump.py
moddump/heroes.py
moddump/i18n.py
moddump/utils.py
moddump.egg-info/PKG-INFO
moddump.egg-info/SOURCES.txt
moddump.egg-info/dependency_links.txt
moddump.egg-info/not-zip-safe
moddump.egg-info/requires.txt
moddump.egg-info/top_level.txt
moddump/locales/dota_brazilian.json
moddump/locales/dota_bulgarian.json
moddump/locales/dota_czech.json
moddump/locales/dota_danish.json
moddump/locales/dota_dutch.json
moddump/locales/dota_english.json
moddump/locales/dota_finnish.json
moddump/locales/dota_french.json
moddump/locales/dota_german.json
moddump/locales/dota_greek.json
moddump/locales/dota_hungarian.json
moddump/locales/dota_italian.json
moddump/locales/dota_japanese.json
moddump/locales/dota_korean.json
moddump/locales/dota_koreana.json
moddump/locales/dota_norwegian.json
moddump/locales/dota_polish.json
moddump/locales/dota_portuguese.json
moddump/locales/dota_romanian.json
moddump/locales/dota_russian.json
moddump/locales/dota_schinese.json
moddump/locales/dota_spanish.json
moddump/locales/dota_swedish.json
moddump/locales/dota_tchinese.json
moddump/locales/dota_thai.json
moddump/locales/dota_turkish.json
moddump/locales/dota_ukrainian.json