Metadata-Version: 1.1
Name: moddump
Version: 0.4
Summary: Dota2 Reborn command line utility to generate a localized JSON of your mod.
Home-page: https://github.com/muZk/moddump
Author: Nicolás Gómez
Author-email: neeco.gmz@gmail.com
License: MIT
Platform: UNKNOWN
Classifier: License :: OSI Approved :: MIT License
Classifier: Intended Audience :: Developers
Classifier: Programming Language :: Python
